{
  "id": "redwood-city-wic-rwc",
  "name": "WIC - RWC",
  "category": "recreation",
  "description": "Women, Infants, and Children (WIC) nutrition program office providing food assistance and health education.",
  "fullDescription": "Women, Infants, and Children (WIC) nutrition program office providing food assistance and health education.",
  "whatTheyOffer": null,
  "howToGetIt": null,
  "groups": [
    "everyone",
    "pregnant",
    "families"
  ],
  "areas": [
    "San Mateo County"
  ],
  "city": "Redwood City",
  "website": "https://www.smchealth.org/wic",
  "cost": null,
  "phone": null,
  "email": null,
  "address": "2342 El Camino Real, Redwood City, CA 94063",
  "requirements": null,
  "howToApply": null,
  "keywords": "WIC, Redwood City, nutrition program, food assistance, pregnant, infants, free WiFi, San Mateo County",
  "lifeEvents": [],
  "agency": null,
  "lastUpdated": "2026-01-19"
}