{
  "id": "redwood-city-motorpool",
  "name": "MotorPool",
  "category": "recreation",
  "description": "Public facility with free WiFi access provided through San Mateo County's public WiFi network.",
  "fullDescription": "Public facility with free WiFi access provided through San Mateo County's public WiFi network.",
  "whatTheyOffer": null,
  "howToGetIt": null,
  "groups": [
    "everyone"
  ],
  "areas": [
    "San Mateo County"
  ],
  "city": "Redwood City",
  "website": "https://www.redwoodcitypar.org/motorpool",
  "cost": null,
  "phone": null,
  "email": null,
  "address": "501 Winslow St, Redwood City, CA 94063",
  "requirements": null,
  "howToApply": null,
  "keywords": "MotorPool, Redwood City, San Mateo County, free WiFi, community space",
  "lifeEvents": [],
  "agency": null,
  "lastUpdated": "2026-01-19"
}