{
  "id": "ap-exam-fee-reductions",
  "name": "AP Exam Fee Reductions",
  "category": "education",
  "description": "$37 College Board fee reduction per exam (schools forgo $9 rebate); final cost typically $53-62 per exam (down from $99); some CA districts provide additional funding bringing cost to $0",
  "eligibility": [
    "low-income"
  ],
  "areas": [
    "Nationwide"
  ],
  "city": null,
  "website": "https://apstudents.collegeboard.org/exam-policies-guidelines/exam-fees",
  "cost": null,
  "phone": null,
  "email": null,
  "requirements": null,
  "howToApply": null,
  "lastUpdated": "2025-12-29"
}