{
  "id": "sfmoma",
  "name": "San Francisco Museum of Modern Art (SFMOMA)",
  "category": "recreation",
  "description": "Free for youth, free days for the public, Museums for All admission for SF residents with benefits cards, military and veteran discounts, and Discover & Go passes",
  "eligibility": [
    "low-income",
    "college-students",
    "veterans",
    "youth",
    "families",
    "everyone"
  ],
  "areas": [
    "San Francisco"
  ],
  "city": null,
  "website": "https://www.sfmoma.org/deals-discounts/",
  "cost": null,
  "phone": null,
  "email": null,
  "requirements": null,
  "howToApply": null,
  "lastUpdated": "2025-12-29"
}